langevin-2025.12.16a4.dist-info/METADATA
langevin-2025.12.16a4.dist-info/WHEEL
langevin/dp/dplvn.cpython-314-darwin.so
langevin/__init__.py
langevin/base/__init__.py
langevin/base/file.py
langevin/base/initialize.py
langevin/base/serialize.py
langevin/base/utils.py
langevin/base/viz.py
langevin/dp/__init__.py
langevin/dp/ensemble.py
langevin/dp/simulation.py
langevin/dp/vizdp.py
langevin-2025.12.16a4.dist-info/RECORD
