Metadata-Version: 2.1
Name: langevin
Version: 2025.12.16a4
Summary: Tools to integrate Langevin equations for directed-percolation and absorbing phase transition models
Keywords: directed percolation,Langevin equation,operator splitting,stochastic differential equations,phase transition
Author-Email: "Colin P. Stark" <cstarkjp@gmail.com>
Classifier: Development Status :: 4 - Beta
Classifier: License :: OSI Approved :: GNU General Public License v3 (GPLv3)
Classifier: Topic :: Scientific/Engineering :: Physics
Classifier: Intended Audience :: Science/Research
Classifier: Programming Language :: C++
Classifier: Programming Language :: Python :: 3
Classifier: Operating System :: MacOS
Classifier: Operating System :: POSIX :: Linux
Classifier: Operating System :: Microsoft :: Windows
Project-URL: homepage, https://cstarkjp.github.io/Langevin
Project-URL: repository, https://github.com/cstarkjp/Langevin
Project-URL: documentation, https://cstarkjp.github.io/Langevin
Requires-Python: >=3.12
Requires-Dist: pybind11
Requires-Dist: numpy
Requires-Dist: jupyter
Requires-Dist: ipython
Requires-Dist: matplotlib
Requires-Dist: pandas
Requires-Dist: tqdm
Requires-Dist: ffmpeg-python
